PoPE/__init__.py
PoPE/plotting_tools.py
PoPE/profile_estimator.py
examples/TNG_example.py
examples/__init__.py
examples/simulated_example.py
examples/visualize_priors.py
PoPE-1.0.3.dist-info/LICENSE
PoPE-1.0.3.dist-info/METADATA
PoPE-1.0.3.dist-info/WHEEL
PoPE-1.0.3.dist-info/top_level.txt
PoPE-1.0.3.dist-info/RECORD
