Metadata-Version: 2.1
Name: PoPE
Version: 1.0.3
Summary: Population Profile Estimator.
Home-page: https://github.com/afarahi/PoPE
Author: Arya Farahi
Author-email: arya.farahi@austin.utexas.edu
License: MIT
Keywords: linear,regression,astronomy,astrophysics,parameter estimation
Platform: UNKNOWN
Classifier: Programming Language :: Python :: 3
Classifier: Programming Language :: Python :: 3.6
Classifier: Programming Language :: Python :: 3.7
Classifier: Programming Language :: Python :: 3.8
Classifier: Programming Language :: Python :: 3.9
Classifier: Intended Audience :: Science/Research
Classifier: License :: OSI Approved :: MIT License
Classifier: Topic :: Scientific/Engineering
Classifier: Topic :: Scientific/Engineering :: Astronomy
Classifier: Topic :: Scientific/Engineering :: Physics
Requires-Dist: numpy
Requires-Dist: scipy
Requires-Dist: matplotlib
Requires-Dist: pandas
Requires-Dist: sklearn
Requires-Dist: theano
Requires-Dist: pymc3
